NNetwork/NNetwork.py
NNetwork/__init__.py
NNetwork-0.2.0.dist-info/LICENSE
NNetwork-0.2.0.dist-info/METADATA
NNetwork-0.2.0.dist-info/WHEEL
NNetwork-0.2.0.dist-info/top_level.txt
NNetwork-0.2.0.dist-info/RECORD
