Metadata-Version: 2.1
Name: NNetwork
Version: 0.2.0
Summary: Custom graph/network/multi-weighted network class based on storing list of neighbors for each nodes (as opposed to edge list) for scalable sampling and searching algorithms
Home-page: https://github.com/HanbaekLyu/NNetwork
Author: Hanbaek Lyu
Author-email: hlyu@math.wisc.edu
License: MIT
Keywords: NNetwork
Classifier: Development Status :: 2 - Pre-Alpha
Classifier: Intended Audience :: Science/Research 
Classifier: License :: OSI Approved :: MIT License
Classifier: Natural Language :: English
Classifier: Programming Language :: Python
Classifier: Programming Language :: Python :: 3
Classifier: Programming Language :: Python :: 3 :: Only
Classifier: Programming Language :: Python :: 3.6
Classifier: Programming Language :: Python :: 3.7
Classifier: Programming Language :: Python :: 3.8
Classifier: Topic :: Scientific/Engineering
Requires-Python: >=3.6
Provides-Extra: test
Provides-Extra: docs
Provides-Extra: setup
Provides-Extra: dev
Provides-Extra: all
License-File: LICENSE
